pocwatchdog/__init__.py
pocwatchdog/task_scheduler.py
pocwatchdog-1.1.6.dist-info/LICENSE
pocwatchdog-1.1.6.dist-info/METADATA
pocwatchdog-1.1.6.dist-info/WHEEL
pocwatchdog-1.1.6.dist-info/top_level.txt
pocwatchdog-1.1.6.dist-info/RECORD
