Metadata-Version: 2.1
Name: pocwatchdog
Version: 1.1.6
Summary: A pocwatchdog package for security monitoring
Author-email: Allen <jiangyangcreate@gmail.com>
Project-URL: Homepage, https://github.com/jiangyangcreate/pocwatchdog
Project-URL: Issues, https://github.com/jiangyangcreate/pocwatchdog/issues
Classifier: Programming Language :: Python :: 3
Classifier: License :: OSI Approved :: Apache Software License
Classifier: Operating System :: OS Independent
Requires-Python: >=3.6
License-File: LICENSE
Requires-Dist: schedule>=1.1.0
